{
  "project_info": {
    "project_number": "508708989361",
    "project_id": "todo-4bfc6",
    "storage_bucket": "todo-4bfc6.appspot.com"
  },
  "client": [
    {
      "client_info": {
        "mobilesdk_app_id": "1:508708989361:android:c9913c91be065840bf3590",
        "android_client_info": {
          "package_name": "com.example.todo"
        }
      },
      "oauth_client": [
        {
          "client_id": "508708989361-eaguupn7h09lv288dk3t4q931ktpj9oq.apps.googleusercontent.com",
          "client_type": 3
        }
      ],
      "api_key": [
        {
          "current_key": "AIzaSyC9WbdCShkvPAMIN7uv8I6D2fK-csoCSaM"
        }
      ],
      "services": {
        "appinvite_service": {
          "other_platform_oauth_client": [
            {
              "client_id": "508708989361-eaguupn7h09lv288dk3t4q931ktpj9oq.apps.googleusercontent.com",
              "client_type": 3
            },
            {
              "client_id": "508708989361-epn37v0guragum72155bojbvlbml9kj3.apps.googleusercontent.com",
              "client_type": 2,
              "ios_info": {
                "bundle_id": "com.example.todo"
              }
            }
          ]
        }
      }
    }
  ],
  "configuration_version": "1"
}